__init__.py
_version.py
traffix.py
traffix-0.1.13.dist-info/LICENSE.txt
traffix-0.1.13.dist-info/METADATA
traffix-0.1.13.dist-info/WHEEL
traffix-0.1.13.dist-info/top_level.txt
traffix-0.1.13.dist-info/RECORD
