Metadata-Version: 2.1
Name: traffix
Version: 0.1.13
Summary: A package for macroscopic transportation assignment.
Home-page: https://github.com/Ultios/traffix
Author: Aulia Rahman
Author-email: rahmancs02@gmail.com
Keywords: Traffic Assignment,Transportation Planning,Macroscopic Transportation Planning
Classifier: Development Status :: 3 - Alpha
Classifier: Programming Language :: Python :: 3
Classifier: Programming Language :: Python :: 3.6
Classifier: Programming Language :: Python :: 3.7
Classifier: Programming Language :: Python :: 3.8
Classifier: Programming Language :: Python :: 3.9
Classifier: License :: OSI Approved :: MIT License
Classifier: Intended Audience :: Science/Research
Classifier: Topic :: Scientific/Engineering :: GIS
Classifier: Operating System :: OS Independent
License-File: LICENSE.txt
Requires-Dist: osmnx (>=1.3.0)
Requires-Dist: pandas (>=1.5)
Requires-Dist: geopandas (>=0.12)
Requires-Dist: matplotlib (>=3.5)
Requires-Dist: networkx (>=2.8)
Requires-Dist: numpy (>=1.23)
Requires-Dist: pyproj (>=3.4)
Requires-Dist: requests (>=2.28)
Requires-Dist: Shapely (>=2.0)
Requires-Dist: openpyxl
